sample_package/__init__.py
sample_package/sample_module.py
python_project_vik-1.2.0.dist-info/LICENSE
python_project_vik-1.2.0.dist-info/METADATA
python_project_vik-1.2.0.dist-info/WHEEL
python_project_vik-1.2.0.dist-info/top_level.txt
python_project_vik-1.2.0.dist-info/RECORD
