Metadata-Version: 2.1
Name: python-project-vik
Version: 1.2.0
Summary: Python project for testing
Home-page: https://github.com/vikramshinde12/python-project
Author: Vikram Shinde
Author-email: vik.shinde@gmail.com
License: UNKNOWN
Platform: UNKNOWN
Classifier: Programming Language :: Python :: 3
Classifier: License :: OSI Approved :: MIT License
Classifier: Operating System :: OS Independent
Classifier: Intended Audience :: Developers
Requires-Python: >=3.7
